README.md
requirements.txt
setup.py
components/__init__.py
components/__main__.py
components/analyze/README.md
components/analyze/__init__.py
components/analyze/requirements.txt
components/analyze/setup.py
components/analyze/model_evaluation/__init__.py
components/analyze/model_evaluation/__install__.py
components/analyze/model_evaluation/__main__.py
components/analyze/model_evaluation/bean/__init__.py
components/analyze/model_evaluation/bean/config.py
components/analyze/model_evaluation/bean/op_info.py
components/analyze/model_evaluation/common/__init__.py
components/analyze/model_evaluation/common/const.py
components/analyze/model_evaluation/common/utils.py
components/analyze/model_evaluation/common/enum/__init__.py
components/analyze/model_evaluation/common/enum/atc_err.py
components/analyze/model_evaluation/common/enum/engine.py
components/analyze/model_evaluation/common/enum/framework.py
components/analyze/model_evaluation/common/enum/onnx_checker_err.py
components/analyze/model_evaluation/common/enum/soc_type.py
components/analyze/model_evaluation/core/__init__.py
components/analyze/model_evaluation/core/analysis.py
components/analyze/model_evaluation/core/result.py
components/analyze/model_evaluation/core/rule.py
components/analyze/model_evaluation/core/checker/__init__.py
components/analyze/model_evaluation/core/checker/onnx.py
components/analyze/model_evaluation/data/__init__.py
components/analyze/model_evaluation/data/op_map.py
components/analyze/model_evaluation/data/opp.py
components/analyze/model_evaluation/data/map_conf/__init__.py
components/analyze/model_evaluation/graph/__init__.py
components/analyze/model_evaluation/graph/onnx.py
components/analyze/model_evaluation/parser/__init__.py
components/analyze/model_evaluation/parser/atc.py
components/analyze/model_evaluation/parser/model.py
components/analyze/model_evaluation/parser/om.py
components/benchmark/README.md
components/benchmark/__init__.py
components/benchmark/setup.py
msit.egg-info/PKG-INFO
msit.egg-info/SOURCES.txt
msit.egg-info/dependency_links.txt
msit.egg-info/entry_points.txt
msit.egg-info/requires.txt
msit.egg-info/top_level.txt