Metadata-Version: 2.1
Name: msit
Version: 8.2.0
Summary: msIT, MindStudio Inference Tools
Home-page: https://gitcode.com/Ascend/msit
License: Apache-2.0
Keywords: msit
Requires-Python: >=3.7
Requires-Dist: numpy<2.0
